README.md
setup.py
./river
pyriver/__init__.py
pyriver/server.py
pyriver/settings.py
pyriver.egg-info/PKG-INFO
pyriver.egg-info/SOURCES.txt
pyriver.egg-info/dependency_links.txt
pyriver.egg-info/entry_points.txt
pyriver.egg-info/requires.txt
pyriver.egg-info/top_level.txt
pyriver/api/__init__.py
pyriver/api/routes.py
pyriver/builtin/__init__.py
pyriver/builtin/build.py
pyriver/builtin/deploy.py
pyriver/builtin/get.py
pyriver/builtin/init.py
pyriver/builtin/run.py
pyriver/builtin/tail.py
pyriver/builtin/up.py
pyriver/db/__init__.py
pyriver/db/database.py
pyriver/engine/__init__.py
pyriver/engine/aggregator.py
pyriver/engine/exception.py
pyriver/engine/listener.py
pyriver/engine/manager.py
pyriver/engine/processor.py
pyriver/engine/source.py
pyriver/engine/stream.py
pyriver/models/__init__.py
pyriver/models/base.py
pyriver/models/channel.py
pyriver/models/event.py
pyriver/models/joins.py
pyriver/models/stream.py
pyriver/services/__init__.py
pyriver/services/channel_service.py
pyriver/services/event_service.py
pyriver/services/stream_service.py