Metadata-Version: 1.0
Name: pyriver
Version: 0.0.1.10
Summary: River client.
Home-page: http://github.com/ptbrodie/pyriver
Author: Patrick Brodie
Author-email: ptbrodie@gmail.com
License: UNKNOWN
Platform: UNKNOWN
